asimov_jq_module/__init__.py
asimov_jq_module/runner/__init__.py
asimov_jq_module/runner/__main__.py
asimov_jq_module/runner/asimov-jq-runner
asimov_jq_module-0.1.3.dist-info/entry_points.txt
asimov_jq_module-0.1.3.dist-info/METADATA
asimov_jq_module-0.1.3.dist-info/WHEEL
asimov_jq_module-0.1.3.dist-info/RECORD
